string_net/__init__.py
string_net/string_net.py
string_net-0.0.3.dist-info/LICENSE
string_net-0.0.3.dist-info/METADATA
string_net-0.0.3.dist-info/WHEEL
string_net-0.0.3.dist-info/top_level.txt
string_net-0.0.3.dist-info/RECORD
