Metadata-Version: 2.1
Name: string-net
Version: 0.0.3
Summary: Observe the ppi network from STRING db.
Home-page: https://github.com/LeonardoNossa/STRING-package.git
Author: Leonardo Nossa
License: LICENSE
Classifier: License :: OSI Approved :: MIT License
Classifier: Programming Language :: Python
Classifier: Operating System :: POSIX
Classifier: Operating System :: Microsoft :: Windows
Requires-Python: >=3.11
License-File: LICENSE
Provides-Extra: dev
Requires-Dist: twine >=5.0.0 ; extra == 'dev'
Requires-Dist: flake8 >=7.0.0 ; extra == 'dev'
Requires-Dist: tox >=4.14.2 ; extra == 'dev'
